odoo/addons/l10n_br_simple/README.rst
odoo/addons/l10n_br_simple/__init__.py
odoo/addons/l10n_br_simple/__manifest__.py
odoo/addons/l10n_br_simple/data/account.account.template.csv
odoo/addons/l10n_br_simple/data/account_chart_template_data.xml
odoo/addons/l10n_br_simple/data/account_group_data.xml
odoo/addons/l10n_br_simple/data/account_tax_group_data.xml
odoo/addons/l10n_br_simple/data/account_tax_template_data.xml
odoo/addons/l10n_br_simple/i18n/l10n_br_simple.pot
odoo/addons/l10n_br_simple/readme/CONFIGURE.rst
odoo/addons/l10n_br_simple/readme/CONTRIBUTORS.rst
odoo/addons/l10n_br_simple/readme/DESCRIPTION.rst
odoo/addons/l10n_br_simple/readme/INSTALL.rst
odoo/addons/l10n_br_simple/readme/ROADMAP.rst
odoo/addons/l10n_br_simple/readme/USAGE.rst
odoo/addons/l10n_br_simple/static/description/icon.png
odoo/addons/l10n_br_simple/static/description/index.html
odoo/addons/l10n_br_simple/tests/__init__.py
odoo/addons/l10n_br_simple/tests/test_l10n_br_simple_coa.py
odoo12_addon_l10n_br_simple-12.0.1.0.0.99.dev17.dist-info/METADATA
odoo12_addon_l10n_br_simple-12.0.1.0.0.99.dev17.dist-info/WHEEL
odoo12_addon_l10n_br_simple-12.0.1.0.0.99.dev17.dist-info/top_level.txt
odoo12_addon_l10n_br_simple-12.0.1.0.0.99.dev17.dist-info/RECORD
