Metadata-Version: 2.1
Name: odoo12-addon-l10n-br-simple
Version: 12.0.1.0.0.99.dev17
Summary: Brazilian Simple Chart of Account
Home-page: http://github.com/OCA/l10n-brazil
Author: Akretion, Odoo Community Association (OCA)
Author-email: support@odoo-community.org
License: AGPL-3
Platform: UNKNOWN
Classifier: Programming Language :: Python
Classifier: Framework :: Odoo
Classifier: License :: OSI Approved :: GNU Affero General Public License v3
Requires-Python: >=3.5
Requires-Dist: odoo (<12.1dev,>=12.0a)
